dcp/__init__.py
dcp/cli/__init__.py
dcp/cli/app.py
dcp/cli/command.py
dcp/cli/helpers.py
dcp/cli/infer.py
dcp/data_copy/__init__.py
dcp/data_copy/base.py
dcp/data_copy/copiers/__init__.py
dcp/data_copy/copiers/to_database/__init__.py
dcp/data_copy/copiers/to_database/database_to_database.py
dcp/data_copy/copiers/to_database/file_to_database.py
dcp/data_copy/copiers/to_database/memory_to_database.py
dcp/data_copy/copiers/to_file/__init__.py
dcp/data_copy/copiers/to_file/database_to_file.py
dcp/data_copy/copiers/to_file/memory_to_file.py
dcp/data_copy/copiers/to_memory/__init__.py
dcp/data_copy/copiers/to_memory/database_to_memory.py
dcp/data_copy/copiers/to_memory/file_to_memory.py
dcp/data_copy/copiers/to_memory/memory_to_memory.py
dcp/data_copy/costs.py
dcp/data_copy/graph.py
dcp/data_copy/helpers.py
dcp/data_format/__init__.py
dcp/data_format/base.py
dcp/data_format/formats/__init__.py
dcp/data_format/formats/database/__init__.py
dcp/data_format/formats/database/base.py
dcp/data_format/formats/database/mysql.py
dcp/data_format/formats/file_system/__init__.py
dcp/data_format/formats/file_system/arrow_file.py
dcp/data_format/formats/file_system/csv_file.py
dcp/data_format/formats/file_system/json_lines_file.py
dcp/data_format/formats/memory/__init__.py
dcp/data_format/formats/memory/arrow_table.py
dcp/data_format/formats/memory/csv_lines_iterator.py
dcp/data_format/formats/memory/database_cursor.py
dcp/data_format/formats/memory/dataframe.py
dcp/data_format/formats/memory/dataframe_iterator.py
dcp/data_format/formats/memory/json_lines_file_object.py
dcp/data_format/formats/memory/records.py
dcp/data_format/formats/memory/records_iterator.py
dcp/data_format/handler.py
dcp/data_format/inference.py
dcp/logging.py
dcp/storage/__init__.py
dcp/storage/base.py
dcp/storage/database/__init__.py
dcp/storage/database/api.py
dcp/storage/database/engines/__init__.py
dcp/storage/database/engines/bigquery.py
dcp/storage/database/engines/mysql.py
datacopy-0.2.1.dist-info/entry_points.txt
datacopy-0.2.1.dist-info/LICENSE
datacopy-0.2.1.dist-info/WHEEL
datacopy-0.2.1.dist-info/METADATA
datacopy-0.2.1.dist-info/RECORD
