Metadata-Version: 2.1
Name: datacopy
Version: 0.2.1
Summary: dcp - Data Copy
License: BSD-3-Clause
Author: Ken Van Haren
Author-email: kenvanharen@gmail.com
Requires-Python: >=3.8.1,<3.11
Classifier: License :: OSI Approved :: BSD License
Classifier: Programming Language :: Python :: 3
Classifier: Programming Language :: Python :: 3.10
Classifier: Programming Language :: Python :: 3.9
Requires-Dist: Jinja2 (>=3.0.3,<4.0.0)
Requires-Dist: PyYAML (>=5.4.1)
Requires-Dist: SQLAlchemy (>=1.4.7,<2.0.0)
Requires-Dist: cleo (>=0.8.1,<0.9.0)
Requires-Dist: clevercsv (>=0.7.4,<0.8.0)
Requires-Dist: common-model (>=0.5.0,<0.6.0)
Requires-Dist: loguru (>=0.5.3,<0.6.0)
Requires-Dist: networkx (>=2.5,<3.0)
Requires-Dist: pandas (>=1.2.3,<2.0.0)
Requires-Dist: python-dateutil (>=2.8.1,<3.0.0)
Requires-Dist: sqlparse (>=0.4.2,<0.5.0)
